README.md
setup.py
geocloud_nmea/__init__.py
geocloud_nmea.egg-info/PKG-INFO
geocloud_nmea.egg-info/SOURCES.txt
geocloud_nmea.egg-info/dependency_links.txt
geocloud_nmea.egg-info/entry_points.txt
geocloud_nmea.egg-info/requires.txt
geocloud_nmea.egg-info/top_level.txt